ccp/__init__.py
ccp/compressor.py
ccp/curve.py
ccp/evaluation.py
ccp/fo.py
ccp/impeller.py
ccp/plotly_theme.py
ccp/point.py
ccp/similarity.py
ccp/state.py
ccp/app/__init__.py
ccp/app/ccp_app.bat
ccp/app/ccp_app.py
ccp/app/common.py
ccp/app/curves-conversion-example.ccp
ccp/app/example_back_to_back.ccp
ccp/app/example_straight.ccp
ccp/app/requirements.txt
ccp/app/.streamlit/config.toml
ccp/app/assets/ccp.png
ccp/app/assets/favicon.ico
ccp/app/assets/style.css
ccp/app/data/.gitkeep
ccp/app/pages/1_straight_through.py
ccp/app/pages/2_back_to_back.py
ccp/app/pages/3_curves_conversion.py
ccp/app/pages/__init__.py
ccp/app/pages/assets/ccp.png
ccp/app/pages/assets/favicon.ico
ccp/app/pages/assets/style.css
ccp/config/__init__.py
ccp/config/fluids.py
ccp/config/legacy_water_units.txt
ccp/config/new_units.txt
ccp/config/units.py
ccp/config/utilities.py
ccp/cprofile/cprofile.py
ccp/data_io/__init__.py
ccp/data_io/processing.py
ccp/data_io/read_csv.py
ccp/data_io/read_xl.py
ccp/tests/test_compressor.py
ccp/tests/test_curve.py
ccp/tests/test_evaluation.py
ccp/tests/test_fo.py
ccp/tests/test_impeller.py
ccp/tests/test_io.py
ccp/tests/test_load_power_shaft.py
ccp/tests/test_point.py
ccp/tests/test_state.py
ccp/tests/test_units.py
ccp/tests/data/UTGCA_1231_A_1s.csv
ccp/tests/data/UTGCA_1231_A_2019-01-01T00_00_00_2020-12-11T00_00_00_12h
ccp/tests/data/data.parquet
ccp/tests/data/data_delta_p.parquet
ccp/tests/data/eval-lp-sec1-caso-a-eff.csv
ccp/tests/data/eval-lp-sec1-caso-a-head.csv
ccp/tests/data/lp-sec1-caso-a-eff.csv
ccp/tests/data/lp-sec1-caso-a-head.csv
ccp/tests/data/normal-eff.csv
ccp/tests/data/normal-head.csv
ccp/tests/data/p78-main-N2-head.csv
ccp/tests/data/p78-main-N2-power_shaft.csv
ccp/utils/find_composition.py
ccp_performance-0.3.29.dist-info/licenses/LICENSE
ccp_performance-0.3.29.dist-info/METADATA
ccp_performance-0.3.29.dist-info/WHEEL
ccp_performance-0.3.29.dist-info/top_level.txt
ccp_performance-0.3.29.dist-info/RECORD
