Metadata-Version: 2.4
Name: ccp-performance
Version: 0.3.29
Summary: Centrifugal Compressor Performance calculation.
Author-email: Raphael Timbó <raphaelts@petrobras.com.br>
License: Apache-2.0
Project-URL: Documentation, https://ccp-centrifugal-compressor-performance.readthedocs.io/en/stable/
Project-URL: Bug Tracker, https://github.com/petrobras/ccp/issues
Project-URL: Source Code, https://github.com/petrobras/ccp
Classifier: Programming Language :: Python
Classifier: Programming Language :: Python :: 3
Classifier: Programming Language :: Python :: 3.6
Classifier: Programming Language :: Python :: 3.7
Classifier: Programming Language :: Python :: 3.8
Classifier: Programming Language :: Python :: 3.9
Classifier: Programming Language :: Python :: 3.10
Classifier: Programming Language :: Python :: 3.11
Classifier: Programming Language :: Python :: Implementation :: CPython
Classifier: Operating System :: OS Independent
Requires-Python: >=3.6
License-File: LICENSE
Requires-Dist: numpy
Requires-Dist: scipy
Requires-Dist: pandas>=0.23
Requires-Dist: CoolProp
Requires-Dist: pint>=0.18
Requires-Dist: plotly>=4.7.0
Requires-Dist: toml>=0.10.1
Requires-Dist: openpyxl
Requires-Dist: tqdm
Requires-Dist: ctREFPROP
Requires-Dist: xlsxwriter
Requires-Dist: scikit-learn
Requires-Dist: xlwings; sys_platform == "win32" or sys_platform == "cygwin" or sys_platform == "msys"
Provides-Extra: dev
Requires-Dist: pytest; extra == "dev"
Requires-Dist: pytest-cov; extra == "dev"
Requires-Dist: coverage; extra == "dev"
Requires-Dist: codecov; extra == "dev"
Requires-Dist: sphinx; extra == "dev"
Requires-Dist: nbsphinx; extra == "dev"
Requires-Dist: numpydoc; extra == "dev"
Requires-Dist: sphinxcontrib-bibtex; extra == "dev"
Requires-Dist: ruff; extra == "dev"
Requires-Dist: myst-nb; extra == "dev"
Requires-Dist: linkify-it-py; extra == "dev"
Requires-Dist: sphinx-book-theme; extra == "dev"
Requires-Dist: sphinx-panels; extra == "dev"
Requires-Dist: sphinx-copybutton; extra == "dev"
Requires-Dist: sphinx-rtd-theme; extra == "dev"
Provides-Extra: app
Requires-Dist: streamlit>=1.21.0; extra == "app"
Requires-Dist: sentry-sdk; extra == "app"
Dynamic: license-file
